zero_width_lib/__init__.py
zero_width_lib/util.py
zero_width_lib-1.0.1.dist-info/METADATA
zero_width_lib-1.0.1.dist-info/WHEEL
zero_width_lib-1.0.1.dist-info/top_level.txt
zero_width_lib-1.0.1.dist-info/RECORD
