Metadata-Version: 2.1
Name: zero-width-lib
Version: 1.0.1
Summary: Zero-width-lib is a library for manipulating zero width characters (ZWC), which are non-printing and invisible chars.
Home-page: https://github.com/shacha086/zero-width-lib-python
Author: shacha086
Author-email: shacha05@outlook.com
License: UNKNOWN
Platform: UNKNOWN
Classifier: Programming Language :: Python :: 3
Classifier: License :: OSI Approved :: MIT License
Classifier: Operating System :: OS Independent
Requires-Python: >=3.6
